pycausal_dai/__init__.py
pycausal_dai/meta_learners.py
pycausal_dai/propensity.py
pycausal_dai/rct.py
pycausal_dai-0.1.1.dist-info/licenses/LICENSE
pycausal_dai-0.1.1.dist-info/METADATA
pycausal_dai-0.1.1.dist-info/WHEEL
pycausal_dai-0.1.1.dist-info/top_level.txt
pycausal_dai-0.1.1.dist-info/RECORD
